pytrellis/__init__.py
pytrellis/_create_empty_dict.py
pytrellis/_flexible_multilevel_mkdir.py
pytrellis-0.0.1.dist-info/LICENSE
pytrellis-0.0.1.dist-info/METADATA
pytrellis-0.0.1.dist-info/WHEEL
pytrellis-0.0.1.dist-info/top_level.txt
pytrellis-0.0.1.dist-info/RECORD
